{
    "id": 936,
    "name": "armarouge",
    "species": "armarouge",
    "latest_game_version": "scarlet-violet",
    "types": [
        "fire",
        "psychic"
    ],
    "base_stats": {
        "hp": 85,
        "attack": 60,
        "defense": 100,
        "special-attack": 125,
        "special-defense": 80,
        "speed": 75
    },
    "bst": 525,
    "abilities": [
        "flash-fire",
        "weak-armor"
    ],
    "moves": [
        "take-down",
        "leer",
        "ember",
        "flamethrower",
        "psybeam",
        "solar-beam",
        "fire-spin",
        "psychic",
        "night-shade",
        "confuse-ray",
        "light-screen",
        "reflect",
        "fire-blast",
        "rest",
        "substitute",
        "spite",
        "protect",
        "endure",
        "sleep-talk",
        "sunny-day",
        "psych-up",
        "shadow-ball",
        "heat-wave",
        "will-o-wisp",
        "facade",
        "taunt",
        "helping-hand",
        "trick",
        "astonish",
        "weather-ball",
        "overheat",
        "iron-defense",
        "calm-mind",
        "fling",
        "flare-blitz",
        "aura-sphere",
        "dark-pulse",
        "dragon-pulse",
        "focus-blast",
        "energy-ball",
        "flash-cannon",
        "trick-room",
        "lava-plume",
        "wide-guard",
        "psyshock",
        "flame-charge",
        "acid-spray",
        "clear-smog",
        "stored-power",
        "ally-switch",
        "incinerate",
        "mystical-fire",
        "psychic-terrain",
        "expanding-force",
        "meteor-beam",
        "scorching-sands",
        "tera-blast",
        "armor-cannon"
    ],
    "sprite_url": "https://raw.githubusercontent.com/PokeAPI/sprites/master/sprites/pokemon/other/official-artwork/936.png"
}