{
    "id": 980,
    "name": "clodsire",
    "species": "clodsire",
    "latest_game_version": "scarlet-violet",
    "types": [
        "poison",
        "ground"
    ],
    "base_stats": {
        "hp": 130,
        "attack": 75,
        "defense": 60,
        "special-attack": 45,
        "special-defense": 100,
        "speed": 20
    },
    "bst": 430,
    "abilities": [
        "poison-point",
        "water-absorb",
        "unaware"
    ],
    "moves": [
        "slam",
        "body-slam",
        "take-down",
        "double-edge",
        "tail-whip",
        "poison-sting",
        "hydro-pump",
        "surf",
        "hyper-beam",
        "low-kick",
        "earthquake",
        "dig",
        "toxic",
        "haze",
        "waterfall",
        "amnesia",
        "rest",
        "rock-slide",
        "substitute",
        "curse",
        "protect",
        "sludge-bomb",
        "mud-slap",
        "spikes",
        "sandstorm",
        "endure",
        "sleep-talk",
        "megahorn",
        "rain-dance",
        "facade",
        "helping-hand",
        "yawn",
        "rock-tomb",
        "muddy-water",
        "mud-shot",
        "poison-tail",
        "water-pulse",
        "toxic-spikes",
        "poison-jab",
        "earth-power",
        "giga-impact",
        "zen-headbutt",
        "gunk-shot",
        "iron-head",
        "stone-edge",
        "stealth-rock",
        "venoshock",
        "sludge-wave",
        "heavy-slam",
        "acid-spray",
        "bulldoze",
        "high-horsepower",
        "stomping-tantrum",
        "liquidation",
        "body-press",
        "tera-blast",
        "trailblaze",
        "chilling-water"
    ],
    "sprite_url": "https://raw.githubusercontent.com/PokeAPI/sprites/master/sprites/pokemon/other/official-artwork/980.png"
}