{
    "id": 51,
    "name": "dugtrio",
    "species": "dugtrio",
    "latest_game_version": "scarlet-violet",
    "types": [
        "ground"
    ],
    "base_stats": {
        "hp": 35,
        "attack": 100,
        "defense": 50,
        "special-attack": 50,
        "special-defense": 70,
        "speed": 120
    },
    "bst": 425,
    "abilities": [
        "sand-veil",
        "arena-trap",
        "sand-force"
    ],
    "moves": [
        "scratch",
        "swords-dance",
        "sand-attack",
        "body-slam",
        "take-down",
        "double-edge",
        "growl",
        "hyper-beam",
        "earthquake",
        "fissure",
        "dig",
        "agility",
        "rest",
        "rock-slide",
        "tri-attack",
        "slash",
        "substitute",
        "thief",
        "curse",
        "reversal",
        "protect",
        "sludge-bomb",
        "mud-slap",
        "sandstorm",
        "endure",
        "charm",
        "sleep-talk",
        "sunny-day",
        "uproar",
        "facade",
        "endeavor",
        "astonish",
        "rock-tomb",
        "sand-tomb",
        "mud-shot",
        "rock-blast",
        "sucker-punch",
        "night-slash",
        "earth-power",
        "giga-impact",
        "shadow-claw",
        "stone-edge",
        "stealth-rock",
        "smack-down",
        "sludge-wave",
        "foul-play",
        "bulldoze",
        "throat-chop",
        "stomping-tantrum",
        "scorching-sands",
        "tera-blast"
    ],
    "sprite_url": "https://raw.githubusercontent.com/PokeAPI/sprites/master/sprites/pokemon/other/official-artwork/51.png"
}