{
    "id": 711,
    "name": "gourgeist-average",
    "species": "gourgeist",
    "latest_game_version": "sword-shield",
    "types": [
        "ghost",
        "grass"
    ],
    "base_stats": {
        "hp": 65,
        "attack": 90,
        "defense": 122,
        "special-attack": 58,
        "special-defense": 75,
        "speed": 84
    },
    "bst": 494,
    "abilities": [
        "pickup",
        "frisk",
        "insomnia"
    ],
    "moves": [
        "flamethrower",
        "hyper-beam",
        "leech-seed",
        "razor-leaf",
        "solar-beam",
        "psychic",
        "confuse-ray",
        "light-screen",
        "fire-blast",
        "explosion",
        "rest",
        "rock-slide",
        "substitute",
        "thief",
        "snore",
        "protect",
        "scary-face",
        "sludge-bomb",
        "giga-drain",
        "endure",
        "attract",
        "sleep-talk",
        "safeguard",
        "pain-split",
        "sunny-day",
        "shadow-ball",
        "will-o-wisp",
        "facade",
        "trick",
        "skill-swap",
        "imprison",
        "astonish",
        "bullet-seed",
        "gyro-ball",
        "worry-seed",
        "dark-pulse",
        "seed-bomb",
        "focus-blast",
        "energy-ball",
        "giga-impact",
        "nasty-plot",
        "shadow-sneak",
        "trick-room",
        "power-whip",
        "grass-knot",
        "foul-play",
        "round",
        "ally-switch",
        "hex",
        "phantom-force",
        "trick-or-treat",
        "moonblast",
        "mystical-fire",
        "brutal-swing",
        "grassy-glide",
        "skitter-smack",
        "poltergeist"
    ],
    "sprite_url": "https://raw.githubusercontent.com/PokeAPI/sprites/master/sprites/pokemon/other/official-artwork/711.png"
}