{
    "id": 862,
    "name": "obstagoon",
    "species": "obstagoon",
    "latest_game_version": "sword-shield",
    "types": [
        "dark",
        "normal"
    ],
    "base_stats": {
        "hp": 93,
        "attack": 90,
        "defense": 101,
        "special-attack": 60,
        "special-defense": 81,
        "speed": 95
    },
    "bst": 520,
    "abilities": [
        "reckless",
        "guts",
        "defiant"
    ],
    "moves": [
        "mega-punch",
        "fire-punch",
        "ice-punch",
        "thunder-punch",
        "mega-kick",
        "sand-attack",
        "headbutt",
        "tackle",
        "body-slam",
        "take-down",
        "double-edge",
        "pin-missile",
        "leer",
        "surf",
        "ice-beam",
        "blizzard",
        "hyper-beam",
        "submission",
        "low-kick",
        "counter",
        "thunderbolt",
        "thunder-wave",
        "thunder",
        "dig",
        "screech",
        "focus-energy",
        "lick",
        "swift",
        "fury-swipes",
        "rest",
        "substitute",
        "thief",
        "snore",
        "reversal",
        "protect",
        "scary-face",
        "icy-wind",
        "endure",
        "attract",
        "sleep-talk",
        "iron-tail",
        "cross-chop",
        "rain-dance",
        "sunny-day",
        "shadow-ball",
        "whirlpool",
        "facade",
        "taunt",
        "helping-hand",
        "trick",
        "revenge",
        "brick-break",
        "hyper-voice",
        "fake-tears",
        "iron-defense",
        "bulk-up",
        "mud-shot",
        "close-combat",
        "payback",
        "assurance",
        "fling",
        "night-slash",
        "seed-bomb",
        "x-scissor",
        "switcheroo",
        "giga-impact",
        "shadow-claw",
        "cross-poison",
        "gunk-shot",
        "grass-knot",
        "hone-claws",
        "round",
        "retaliate",
        "work-up",
        "snarl",
        "baby-doll-eyes",
        "throat-chop",
        "stomping-tantrum",
        "body-press",
        "obstruct",
        "lash-out"
    ],
    "sprite_url": "https://raw.githubusercontent.com/PokeAPI/sprites/master/sprites/pokemon/other/official-artwork/862.png"
}