{
    "id": 10129,
    "name": "salazzle-totem",
    "species": "salazzle",
    "latest_game_version": "scarlet-violet",
    "types": [
        "poison",
        "fire"
    ],
    "base_stats": {
        "hp": 68,
        "attack": 64,
        "defense": 60,
        "special-attack": 111,
        "special-defense": 60,
        "speed": 117
    },
    "bst": 480,
    "abilities": [
        "corrosion",
        "oblivious"
    ],
    "moves": [
        "pound",
        "scratch",
        "body-slam",
        "take-down",
        "disable",
        "ember",
        "flamethrower",
        "hyper-beam",
        "thunder-wave",
        "toxic",
        "agility",
        "smog",
        "fire-blast",
        "swift",
        "poison-gas",
        "leech-life",
        "rest",
        "substitute",
        "thief",
        "protect",
        "scary-face",
        "sludge-bomb",
        "mud-slap",
        "endure",
        "swagger",
        "sleep-talk",
        "encore",
        "sweet-scent",
        "sunny-day",
        "heat-wave",
        "torment",
        "will-o-wisp",
        "facade",
        "taunt",
        "helping-hand",
        "knock-off",
        "endeavor",
        "hyper-voice",
        "poison-fang",
        "fake-tears",
        "overheat",
        "dragon-claw",
        "poison-tail",
        "dragon-dance",
        "fling",
        "toxic-spikes",
        "flare-blitz",
        "poison-jab",
        "dragon-pulse",
        "giga-impact",
        "nasty-plot",
        "shadow-claw",
        "fire-fang",
        "gunk-shot",
        "venoshock",
        "sludge-wave",
        "acid-spray",
        "foul-play",
        "incinerate",
        "acrobatics",
        "fire-lash",
        "breaking-swipe",
        "scale-shot",
        "skitter-smack",
        "burning-jealousy",
        "tera-blast",
        "trailblaze",
        "dragon-cheer",
        "temper-flare"
    ],
    "sprite_url": "https://raw.githubusercontent.com/PokeAPI/sprites/master/sprites/pokemon/other/official-artwork/10129.png"
}