{
    "id": 539,
    "name": "sawk",
    "species": "sawk",
    "latest_game_version": "sword-shield",
    "types": [
        "fighting"
    ],
    "base_stats": {
        "hp": 75,
        "attack": 125,
        "defense": 75,
        "special-attack": 30,
        "special-defense": 75,
        "speed": 85
    },
    "bst": 465,
    "abilities": [
        "sturdy",
        "inner-focus",
        "mold-breaker"
    ],
    "moves": [
        "mega-punch",
        "fire-punch",
        "ice-punch",
        "thunder-punch",
        "double-kick",
        "mega-kick",
        "leer",
        "low-kick",
        "counter",
        "earthquake",
        "dig",
        "focus-energy",
        "rest",
        "rock-slide",
        "substitute",
        "snore",
        "reversal",
        "protect",
        "scary-face",
        "endure",
        "attract",
        "sleep-talk",
        "rain-dance",
        "sunny-day",
        "rock-smash",
        "facade",
        "taunt",
        "helping-hand",
        "superpower",
        "revenge",
        "brick-break",
        "rock-tomb",
        "bulk-up",
        "close-combat",
        "payback",
        "fling",
        "poison-jab",
        "focus-blast",
        "giga-impact",
        "zen-headbutt",
        "stone-edge",
        "grass-knot",
        "low-sweep",
        "round",
        "quick-guard",
        "retaliate",
        "bulldoze",
        "work-up",
        "throat-chop",
        "coaching"
    ],
    "sprite_url": "https://raw.githubusercontent.com/PokeAPI/sprites/master/sprites/pokemon/other/official-artwork/539.png"
}