{
    "id": 220,
    "name": "swinub",
    "species": "swinub",
    "latest_game_version": "scarlet-violet",
    "types": [
        "ice",
        "ground"
    ],
    "base_stats": {
        "hp": 50,
        "attack": 50,
        "defense": 40,
        "special-attack": 30,
        "special-defense": 30,
        "speed": 50
    },
    "bst": 250,
    "abilities": [
        "oblivious",
        "snow-cloak",
        "thick-fat"
    ],
    "moves": [
        "tackle",
        "body-slam",
        "take-down",
        "double-edge",
        "bite",
        "roar",
        "mist",
        "ice-beam",
        "blizzard",
        "earthquake",
        "fissure",
        "dig",
        "haze",
        "amnesia",
        "rest",
        "rock-slide",
        "substitute",
        "curse",
        "flail",
        "reversal",
        "powder-snow",
        "protect",
        "scary-face",
        "mud-slap",
        "icy-wind",
        "sandstorm",
        "endure",
        "charm",
        "sleep-talk",
        "rain-dance",
        "ancient-power",
        "facade",
        "endeavor",
        "rock-tomb",
        "sand-tomb",
        "icicle-spear",
        "mud-shot",
        "earth-power",
        "avalanche",
        "ice-shard",
        "ice-fang",
        "stone-edge",
        "stealth-rock",
        "smack-down",
        "bulldoze",
        "icicle-crash",
        "freeze-dry",
        "high-horsepower",
        "stomping-tantrum",
        "tera-blast",
        "snowscape",
        "trailblaze"
    ],
    "sprite_url": "https://raw.githubusercontent.com/PokeAPI/sprites/master/sprites/pokemon/other/official-artwork/220.png"
}