{
    "id": 72,
    "name": "tentacool",
    "species": "tentacool",
    "latest_game_version": "scarlet-violet",
    "types": [
        "water",
        "poison"
    ],
    "base_stats": {
        "hp": 40,
        "attack": 40,
        "defense": 35,
        "special-attack": 50,
        "special-defense": 100,
        "speed": 70
    },
    "bst": 335,
    "abilities": [
        "clear-body",
        "liquid-ooze",
        "rain-dish"
    ],
    "moves": [
        "swords-dance",
        "wrap",
        "poison-sting",
        "supersonic",
        "acid",
        "water-gun",
        "hydro-pump",
        "surf",
        "ice-beam",
        "blizzard",
        "bubble-beam",
        "aurora-beam",
        "toxic",
        "screech",
        "confuse-ray",
        "haze",
        "swift",
        "acid-armor",
        "rest",
        "substitute",
        "thief",
        "protect",
        "sludge-bomb",
        "icy-wind",
        "giga-drain",
        "endure",
        "sleep-talk",
        "rapid-spin",
        "rain-dance",
        "mirror-coat",
        "whirlpool",
        "facade",
        "knock-off",
        "tickle",
        "muddy-water",
        "mud-shot",
        "water-pulse",
        "acupressure",
        "toxic-spikes",
        "aqua-ring",
        "poison-jab",
        "gunk-shot",
        "venoshock",
        "sludge-wave",
        "acid-spray",
        "hex",
        "dazzling-gleam",
        "throat-chop",
        "liquidation",
        "flip-turn",
        "tera-blast",
        "pounce",
        "chilling-water"
    ],
    "sprite_url": "https://raw.githubusercontent.com/PokeAPI/sprites/master/sprites/pokemon/other/official-artwork/72.png"
}